odoo8_addon_web_widget_datepicker_options-8.0.1.0.0-py2.7-nspkg.pth
odoo_addons/web_widget_datepicker_options/__openerp__.py
odoo_addons/web_widget_datepicker_options/__init__.py
odoo_addons/web_widget_datepicker_options/README.rst
odoo_addons/web_widget_datepicker_options/view/qweb.xml
odoo_addons/web_widget_datepicker_options/static/description/icon.svg
odoo_addons/web_widget_datepicker_options/static/description/icon.png
odoo_addons/web_widget_datepicker_options/static/src/js/datepicker.js
odoo8_addon_web_widget_datepicker_options-8.0.1.0.0.dist-info/top_level.txt
odoo8_addon_web_widget_datepicker_options-8.0.1.0.0.dist-info/WHEEL
odoo8_addon_web_widget_datepicker_options-8.0.1.0.0.dist-info/RECORD
odoo8_addon_web_widget_datepicker_options-8.0.1.0.0.dist-info/metadata.json
odoo8_addon_web_widget_datepicker_options-8.0.1.0.0.dist-info/DESCRIPTION.rst
odoo8_addon_web_widget_datepicker_options-8.0.1.0.0.dist-info/METADATA
odoo8_addon_web_widget_datepicker_options-8.0.1.0.0.dist-info/namespace_packages.txt
